asura/web.py
asura-0.0.2.dist-info/METADATA
asura-0.0.2.dist-info/WHEEL
asura-0.0.2.dist-info/top_level.txt
asura-0.0.2.dist-info/RECORD
