Metadata-Version: 2.1
Name: asura
Version: 0.0.2
Summary: A package that I'm gonna use a lot.
Home-page: UNKNOWN
Author: Simon G.
Author-email: joe@who.joemama
License: UNKNOWN
Platform: UNKNOWN
Requires-Python: >=3.9
